{"inkVersion":21,"root":[[{"->":"marx_scene"},["done",{"#f":5,"#n":"g-0"}],null],"done",{"marx_scene":[["^Căn phòng mang hơi thở công nghiệp — ánh sáng đỏ rỉ qua những ô cửa sổ cao phủ bụi.","\n","^Không khí rung nhẹ, như thể có một cỗ máy khổng lồ ngay sau bức tường chưa bao giờ ngừng vận hành.","\n","^Karl Marx đứng trước nó, áo khoác mở, khuôn mặt được hắt sáng bởi ánh kim loại nóng chảy.","\n","^Ông không nhìn ngươi — ông nhìn thế giới. ","#","^speaker:marx","/#","\n","^Marx: Ngươi mang mùi của lao động, không phải của đức hạnh.","\n","^Mỗi kẻ lao động đều giết đi một phần con người mình. Mỗi kẻ giết đều đang làm việc cho kẻ giàu hơn.","\n","^Nói ta nghe, người lính — khi ngươi phục vụ, ai là kẻ thu lợi? ","#","^speaker:marx","/#","\n","ev","str","^Không ai cả.","/str","/ev",{"*":".^.c-0","flg":20},"ev","str","^Kẻ quyền lực.","/str","/ev",{"*":".^.c-1","flg":20},"ev","str","^Ta không biết.","/str","/ev",{"*":".^.c-2","flg":20},"ev","str","^Ta phục vụ Tổ quốc.","/str","/ev",{"*":".^.c-3","flg":20},{"c-0":["^ Không ai cả. Chỉ là hỗn loạn thôi. ","#","^moral:chaos:+2 ","/#","#","^moral:pessimism:+1  ","/#","\n","ev",{"VAR?":"chaos"},2,"+",{"VAR=":"chaos","re":true},"/ev","ev",{"VAR?":"pessimism"},1,"+",{"VAR=":"pessimism","re":true},"/ev","^Marx: Hỗn loạn chỉ là câu chuyện do những kẻ cai trị trật tự kể ra.","\n","^Ngay cả điên loạn cũng có kế toán của nó. Mỗi viên đạn, mỗi khẩu phần, mỗi xác chết — đều được trả giá, sở hữu, ghi lại. ","#","^speaker:marx","/#","\n",{"->":"marx_reflection"},{"#f":5}],"c-1":["^ Những kẻ an toàn sau tấm màn. ","#","^moral:idealism:+1 ","/#","#","^moral:pessimism:+1  ","/#","\n","ev",{"VAR?":"idealism"},1,"+",{"VAR=":"idealism","re":true},"/ev","ev",{"VAR?":"pessimism"},1,"+",{"VAR=":"pessimism","re":true},"/ev","^Marx: Đúng vậy. Những lãnh chúa của sự tiện nghi — họ xây thiên đường bằng xương người.","\n","^Ngươi mang gánh nặng để họ hát thánh ca ca ngợi lợi nhuận. ","#","^speaker:marx","/#","\n",{"->":"marx_reflection"},{"#f":5}],"c-2":["^ Ta chỉ làm theo lệnh. ","#","^moral:order:+1 ","/#","#","^moral:pessimism:+1  ","/#","\n","ev",{"VAR?":"order"},1,"+",{"VAR=":"order","re":true},"/ev","ev",{"VAR?":"pessimism"},1,"+",{"VAR=":"pessimism","re":true},"/ev","^Marx: Sự vâng lời — hình thức lao động rẻ nhất.","\n","^Tâm trí trở thành giám sát viên của chính xiềng xích mình. ","#","^speaker:marx","/#","\n",{"->":"marx_reflection"},{"#f":5}],"c-3":["^ Ta phục vụ Tổ quốc. Thế là đủ rồi. ","#","^moral:order:+2 ","/#","#","^moral:idealism:+1  ","/#","\n","ev",{"VAR?":"order"},2,"+",{"VAR=":"order","re":true},"/ev","ev",{"VAR?":"idealism"},1,"+",{"VAR=":"idealism","re":true},"/ev","^Marx: “Tổ quốc” — từ ngữ đẹp đẽ nhất để che giấu lá cờ của kẻ sở hữu.","\n","^Chúng vẽ ranh giới quanh máu ngươi và gọi đó là lòng yêu nước. ","#","^speaker:marx","/#","\n",{"->":"marx_reflection"},{"#f":5}]}],{"#f":1}],"marx_reflection":[["^Marx bước đi, tiếng giày dội trên nền bê tông.","\n","^Mỗi bước chân như nhịp búa của nhà máy vẫn đang nghiền nát kẻ nghèo thành bụi.","\n","^Ông dừng lại, nhìn xuống sàn như thấy hồn ma trong những vết dầu loang. ","#","^speaker:marx","/#","\n","^Marx: Ta từng mơ về một thế giới nơi lao động giải phóng con người — nơi công việc xây nên phẩm giá, chứ không phải nợ nần.","\n","^Nhưng rồi lao động lại trở thành xiềng xích.","\n","^Người công nhân bán từng giờ, từng phần thân thể, từng khoảng im lặng… cho đến khi không còn gì để bán ngoài ký ức về chính mình.","\n","^Ngươi đã thấy giấc mơ ấy chết chưa? ","#","^speaker:marx","/#","\n","ev","str","^Ta đã thấy tệ hơn.","/str","/ev",{"*":".^.c-0","flg":20},"ev","str","^Công việc từng cho ta mục đích.","/str","/ev",{"*":".^.c-1","flg":20},"ev","str","^Không ai xứng đáng tự do.","/str","/ev",{"*":".^.c-2","flg":20},"ev","str","^Chẳng liên quan gì đến ta.","/str","/ev",{"*":".^.c-3","flg":20},{"c-0":["^ Giấc mơ chết lặng lẽ. Con người chết ầm ỹ. ","#","^moral:pessimism:+2 ","/#","#","^moral:chaos:+1  ","/#","\n","ev",{"VAR?":"pessimism"},2,"+",{"VAR=":"pessimism","re":true},"/ev","ev",{"VAR?":"chaos"},1,"+",{"VAR=":"chaos","re":true},"/ev","^Marx: Và thế giới vỗ tay cho cả hai.","\n","^Thị trường gọi đó là hiệu suất. Nhà thờ gọi đó là hiến tế.","\n","^Còn ta gọi đó là ăn cắp — ở quy mô thần thánh. ","#","^speaker:marx","/#","\n",{"->":"marx_tyranny"},{"#f":5}],"c-1":["^ Cho đến khi ta ngừng tin vào nó. ","#","^moral:idealism:+1 ","/#","#","^moral:pessimism:+1  ","/#","\n","ev",{"VAR?":"idealism"},1,"+",{"VAR=":"idealism","re":true},"/ev","ev",{"VAR?":"pessimism"},1,"+",{"VAR=":"pessimism","re":true},"/ev","^Marx: “Mục đích” là món hàng đầu tiên họ bán cho ngươi — và là thứ cuối cùng họ tước đi.","\n","^Khi mục đích sụp đổ, ngươi thấy bánh răng đang quay. Và nhận ra: chẳng ai lái cả. ","#","^speaker:marx","/#","\n",{"->":"marx_tyranny"},{"#f":5}],"c-2":["^ Ai cũng phục vụ một thứ gì đó. ","#","^moral:pessimism:+2 ","/#","#","^moral:order:+1  ","/#","\n","ev",{"VAR?":"pessimism"},2,"+",{"VAR=":"pessimism","re":true},"/ev","ev",{"VAR?":"order"},1,"+",{"VAR=":"order","re":true},"/ev","^Marx: Một sự thật cay đắng, nhưng chỉ đúng một nửa.","\n","^Nửa còn lại là thế này: sự phục vụ chỉ trở thành nô lệ khi kẻ chủ nói dối về thần tính của hắn. ","#","^speaker:marx","/#","\n",{"->":"marx_tyranny"},{"#f":5}],"c-3":["^ Thế giới đã hỏng. Ta không sửa nó đâu. ","#","^moral:chaos:+2 ","/#","#","^moral:materialism:+1  ","/#","\n","ev",{"VAR?":"chaos"},2,"+",{"VAR=":"chaos","re":true},"/ev","ev",{"VAR?":"materialism"},1,"+",{"VAR=":"materialism","re":true},"/ev","^Marx: Giai cấp tư sản cảm ơn ngươi vì sự buông xuôi ấy.","\n","^Mỗi người ngừng chiến đấu là thêm một viên gạch trong pháo đài của chúng. ","#","^speaker:marx","/#","\n",{"->":"marx_tyranny"},{"#f":5}]}],{"#f":1}],"marx_tyranny":[["^Giọng Marx thay đổi — không lớn hơn, mà nặng hơn, mỗi từ rơi xuống như một bản án.","\n","^Ông chỉ tay về phía cỗ máy vô hình.","\n","^Tiếng rung của nó vang to hơn, như tiếng hô của một đám đông dưới búa sắt. ","#","^speaker:marx","/#","\n","^Marx: Họ gọi đó là “tiến bộ”.","\n","^Nhưng mọi đế chế, mọi nền cộng hòa, mọi “trật tự” — đều là cùng một lò luyện.","\n","^Kẻ nghèo cháy, kẻ giàu sưởi ấm bàn tay, và tro tàn được gọi là lịch sử.","\n","^Ngươi biết điều khiến ta sợ nhất không, người lính?","\n","^Một ngày nào đó, ngay cả tro tàn cũng quên rằng chúng từng là con người. ","#","^speaker:marx","/#","\n","ev","str","^Vậy hãy đốt sạch tất cả.","/str","/ev",{"*":".^.c-0","flg":20},"ev","str","^Phải có con đường tốt hơn.","/str","/ev",{"*":".^.c-1","flg":20},"ev","str","^Cỗ máy không thể dừng.","/str","/ev",{"*":".^.c-2","flg":20},"ev","str","^Hãy để kẻ giàu thối rữa cùng kẻ nghèo.","/str","/ev",{"*":".^.c-3","flg":20},{"c-0":["^ Có lẽ ta nên bắt đầu lại từ số không. ","#","^moral:chaos:+2 ","/#","#","^moral:pessimism:+1  ","/#","\n","ev",{"VAR?":"chaos"},2,"+",{"VAR=":"chaos","re":true},"/ev","ev",{"VAR?":"pessimism"},1,"+",{"VAR=":"pessimism","re":true},"/ev","^Marx: Ngươi nghĩ ngọn lửa cứu rỗi được tàn tro. Sai rồi.","\n","^Lửa chẳng phục vụ ý thức hệ nào. Cỗ máy sẽ tự tái sinh từ chính cuộc nổi loạn của ngươi. ","#","^speaker:marx","/#","\n",{"->":"marx_final"},{"#f":5}],"c-1":["^ Một thứ vượt khỏi máu và lao động. ","#","^moral:idealism:+2 ","/#","#","^moral:order:+1  ","/#","\n","ev",{"VAR?":"idealism"},2,"+",{"VAR=":"idealism","re":true},"/ev","ev",{"VAR?":"order"},1,"+",{"VAR=":"order","re":true},"/ev","^Marx: Có thể từng tồn tại.","\n","^Nhưng mọi ý tưởng cao quý đều trở thành khẩu hiệu nhà máy khi nó bắt đầu có giá. ","#","^speaker:marx","/#","\n",{"->":"marx_final"},{"#f":5}],"c-2":["^ Vậy sao phải cố? ","#","^moral:pessimism:+2 ","/#","#","^moral:order:+1  ","/#","\n","ev",{"VAR?":"pessimism"},2,"+",{"VAR=":"pessimism","re":true},"/ev","ev",{"VAR?":"order"},1,"+",{"VAR=":"order","re":true},"/ev","^Marx: Thế là ngươi đã chấp nhận nô lệ như một dạng tỉnh táo.","\n","^Lịch sử yêu những kẻ như ngươi — những người khiến xiềng xích trở nên vô hình. ","#","^speaker:marx","/#","\n",{"->":"marx_final"},{"#f":5}],"c-3":["^ Bình đẳng trong đổ nát. ","#","^moral:chaos:+1 ","/#","#","^moral:pessimism:+1  ","/#","\n","ev",{"VAR?":"chaos"},1,"+",{"VAR=":"chaos","re":true},"/ev","ev",{"VAR?":"pessimism"},1,"+",{"VAR=":"pessimism","re":true},"/ev","^Marx: Ngươi nhầm lẫn giữa hủy diệt và công lý.","\n","^Nghĩa trang thì bình đẳng, đúng vậy — nhưng nó cũng im lặng. ","#","^speaker:marx","/#","\n",{"->":"marx_final"},{"#f":5}]}],{"#f":1}],"marx_final":[["^Tiếng máy lắng xuống. Sự im lặng nuốt chửng căn phòng như một bản án.","\n","^Marx đứng yên — lần đầu tiên, ông nhìn thẳng vào ngươi. Ánh mắt không giận dữ, mà thất vọng.","\n","^Nỗi thất vọng dành cho cả giống loài. ","#","^speaker:marx","/#","\n","^Marx: Ta đã trao cho thế giới một lời tiên tri.","\n","^Chúng biến nó thành cẩm nang quyền lực.","\n","^Ngay cả cách mạng cũng trở thành món hàng.","\n","^Ông bước đến gần, giọng nói như sắt kéo lê trên kính.","\n","^Marx: Ngươi tưởng nỗi đau của mình là duy nhất.","\n","^Không đâu.","\n","^Nó là triệu chứng của một cấu trúc ăn sạch mọi thứ — kể cả những kẻ chống lại nó.","\n","^Và ngươi, hỡi người thợ của cái chết, chỉ là một bánh răng đang hỏi tại sao bánh răng khác lại nghiền nát. ","#","^speaker:marx","/#","\n","ev","str","^Vậy thì ý nghĩa là gì?","/str","/ev",{"*":".^.c-0","flg":20},"ev","str","^Vậy ta vẫn sẽ chiến đấu.","/str","/ev",{"*":".^.c-1","flg":20},"ev","str","^Vậy ta sẽ phục vụ nó.","/str","/ev",{"*":".^.c-2","flg":20},"ev","str","^Không ai sở hữu ta.","/str","/ev",{"*":".^.c-3","flg":20},{"c-0":["^ Tại sao phải chiến đấu? ","#","^moral:pessimism:+2  ","/#","\n","ev",{"VAR?":"pessimism"},2,"+",{"VAR=":"pessimism","re":true},"/ev","^Marx: Không có ý nghĩa nào cả. Chỉ có đấu tranh.","\n","^Ý nghĩa là thứ được rèn ra, không phải được tìm thấy — và đa phần tan chảy trước khi kim loại kịp nguội. ","#","^speaker:marx","/#","\n",{"->":"marx_scene_end"},{"#f":5}],"c-1":["^ Chỉ để khinh miệt cỗ máy. ","#","^moral:idealism:+2 ","/#","#","^moral:chaos:+1  ","/#","\n","ev",{"VAR?":"idealism"},2,"+",{"VAR=":"idealism","re":true},"/ev","ev",{"VAR?":"chaos"},1,"+",{"VAR=":"chaos","re":true},"/ev","^Marx: Tốt. Sự khinh miệt cũng có nét thuần khiết riêng.","\n","^Dù là kháng cự tuyệt vọng, nó vẫn nuôi dưỡng huyền thoại về tự do.","\n","^Hãy để huyền thoại ấy sống lâu hơn chúng ta. ","#","^speaker:marx","/#","\n",{"->":"marx_scene_end"},{"#f":5}],"c-2":["^ Ít ra còn trung thực. ","#","^moral:materialism:+1 ","/#","#","^moral:pessimism:+1  ","/#","\n","ev",{"VAR?":"materialism"},1,"+",{"VAR=":"materialism","re":true},"/ev","ev",{"VAR?":"pessimism"},1,"+",{"VAR=":"pessimism","re":true},"/ev","^Marx: Mọi cỗ máy đều yêu kẻ thú nhận với nó.","\n","^Nhưng thú nhận không phải là giải thoát — mà là đầu hàng. ","#","^speaker:marx","/#","\n",{"->":"marx_scene_end"},{"#f":5}],"c-3":["^ Ta từ chối mọi phe phái. ","#","^moral:chaos:+2 ","/#","#","^moral:rationalism:+1  ","/#","\n","ev",{"VAR?":"chaos"},2,"+",{"VAR=":"chaos","re":true},"/ev","ev",{"VAR?":"rationalism"},1,"+",{"VAR=":"rationalism","re":true},"/ev","^Marx: Thế là ngươi đã biến mình thành một nền kinh tế riêng — tự cung tự cấp, tự tiêu diệt.","\n","^Tự do không có mục đích chỉ là hỗn loạn nằm trong quan tài. ","#","^speaker:marx","/#","\n",{"->":"marx_scene_end"},{"#f":5}]}],{"#f":1}],"marx_scene_end":["^Lò luyện rên rỉ. Tàn lửa rơi xuống như những vì sao hấp hối.","\n","^Marx quay lưng lại, hai tay đan sau lưng. ","#","^speaker:marx","/#","\n","^Marx: Lịch sử là sổ cái của đồ tể, viết bằng lửa.","\n","^Con người sống, chịu đựng, và gọi đó là “tiến bộ”.","\n","^Nếu cứu rỗi tồn tại, nó sẽ không rơi xuống từ trời.","\n","^Nó sẽ bò ra từ đống tro tàn, mang tro trong phổi, và tự gọi mình là “thay đổi.” ","#","^speaker:marx","/#","\n","^Ông dừng lại.","\n","^Marx: Ngươi đã thấy điều tệ nhất của loài người.","\n","^Giờ nói đi, người lính — ngươi sẽ nhập vào đống xác, hay thành ngọn lửa thiêu chúng? ","#","^speaker:marx","/#","\n","done",{"#f":1}],"global decl":["ev",0,{"VAR=":"idealism"},0,{"VAR=":"materialism"},0,{"VAR=":"rationalism"},0,{"VAR=":"empiricism"},0,{"VAR=":"order"},0,{"VAR=":"chaos"},0,{"VAR=":"pessimism"},"/ev","end",null],"#f":1}],"listDefs":{}}